{
  "ingredients": [
    {
      "text": "2 cups flour"
    },
    {
      "text": "1 tablespoon cinnamon"
    },
    {
      "text": "2 teaspoons baking soda"
    },
    {
      "text": "1 teaspoon salt"
    },
    {
      "text": "14 teaspoon baking powder"
    },
    {
      "text": "3 eggs"
    },
    {
      "text": "2 cups sugar"
    },
    {
      "text": "1 cup vegetable oil"
    },
    {
      "text": "1 tablespoon vanilla"
    },
    {
      "text": "2 cups grated raw zucchini"
    },
    {
      "text": "1 cup walnuts"
    }
  ],
  "url": "http://www.food.com/recipe/zucchini-nut-bread-329682",
  "title": "Zucchini Nut Bread",
  "instructions": [
    {
      "text": "Sift dry ingredients."
    },
    {
      "text": "beat eggs untill frothy, add sugar, oil and vanilla."
    },
    {
      "text": "Beat untillthick."
    },
    {
      "text": "Stir in zucchini."
    },
    {
      "text": "blend in sifted dry ingredients."
    },
    {
      "text": "Fold in nuts."
    },
    {
      "text": "pour in greased loaf pan and bake at 350 degrees for 1 1/2 hours."
    }
  ],
  "image": ""
}